.gitignore
CONTRIBUTING
COPYING
Makefile
README.md
_mpmetrics.c
_mpmetrics.h
atomic.c
atomic.h
lock.c
setup.py
.github/workflows/doc.yml
.github/workflows/python.yml
LICENSES/Apache-2.0.txt
LICENSES/CC-BY-SA-3.0.txt
LICENSES/GPL-3.0-only.txt
LICENSES/LGPL-3.0-only.txt
LICENSES/MIT.txt
doc/conf.py
doc/index.rst
doc/internals.rst
doc/mpmetrics.rst
examples/README.md
examples/flask_client.py
examples/flask_server.py
examples/readme.py
mpmetrics/__init__.py
mpmetrics/atomic.py
mpmetrics/flask.py
mpmetrics/generics.py
mpmetrics/heap.py
mpmetrics/metrics.py
mpmetrics/types.py
mpmetrics/util.py
mpmetrics.egg-info/PKG-INFO
mpmetrics.egg-info/SOURCES.txt
mpmetrics.egg-info/dependency_links.txt
mpmetrics.egg-info/requires.txt
mpmetrics.egg-info/top_level.txt
tests/__init__.py
tests/atomic_test.py
tests/common.py
tests/examples_test.py
tests/heap_test.py
tests/lock_test.py
tests/metric_test.py
tests/types_test.py
tests/util_test.py