Metadata-Version: 2.1
Name: mpmetrics
Version: 0.1.0
Summary: Multiprocess-safe metrics
Home-page: https://github.com/Forty-Bot/mpmetrics
Author: Sean Anderson
Author-email: seanga2@gmail.com
License: LGPL-3.0-only
Requires-Python: >=3.9
License-File: COPYING
License-File: LICENSES/Apache-2.0.txt
License-File: LICENSES/CC-BY-SA-3.0.txt
License-File: LICENSES/GPL-3.0-only.txt
License-File: LICENSES/LGPL-3.0-only.txt
License-File: LICENSES/MIT.txt
Requires-Dist: prometheus_client
Provides-Extra: doc
Requires-Dist: sphinx; extra == "doc"
Requires-Dist: sphinx-rtd-theme; extra == "doc"
Provides-Extra: flask
Requires-Dist: prometheus_flask_exporter; extra == "flask"
Provides-Extra: tests
Requires-Dist: flask; extra == "tests"
Requires-Dist: freezegun; extra == "tests"
Requires-Dist: hypothesis; extra == "tests"
Requires-Dist: prometheus_flask_exporter; extra == "tests"
Requires-Dist: pytest; extra == "tests"
